setup.py
ut61e/__init__.py
ut61e/es51922.py
ut61e/he2325u_hidapi.py
ut61e/he2325u_pyusb.py
ut61e.egg-info/PKG-INFO
ut61e.egg-info/SOURCES.txt
ut61e.egg-info/dependency_links.txt
ut61e.egg-info/entry_points.txt
ut61e.egg-info/requires.txt
ut61e.egg-info/top_level.txt