Metadata-Version: 1.1
Name: ut61e
Version: 1.0.2
Summary: Connect your Digital Multimeter Uni-T UT61E with Python!
Home-page: https://github.com/pklaus/ut61e_python
Author: Philipp Klaus
Author-email: philipp.l.klaus@web.de
License: GPL
Keywords: UNI-T UT61E DMM digital multimeter
Platform: UNKNOWN
Classifier: Development Status :: 4 - Beta
Classifier: Operating System :: OS Independent
Classifier: License :: OSI Approved :: GNU General Public License v3 (GPLv3)
Classifier: Programming Language :: Python
Classifier: Programming Language :: Python :: 2
Classifier: Programming Language :: Python :: 2.7
Classifier: Programming Language :: Python :: 3
Classifier: Programming Language :: Python :: 3.3
Classifier: Topic :: System :: Hardware :: Hardware Drivers
Classifier: Topic :: Scientific/Engineering
